[
   {
      "2013": {
         "Negative": 0.4746281669543644,
         "Neutral": 0.34085457681707565,
         "Positive": 0.18451725622855997
      }
   },
   {
      "2014": {
         "Negative": 0.5134993418798754,
         "Neutral": 0.33256274204819025,
         "Positive": 0.15393791607193427
      }
   },
   {
      "2015": {
         "Negative": 0.5168403710838687,
         "Neutral": 0.3204070494568264,
         "Positive": 0.1627525794593049
      }
   },
   {
      "2016": {
         "Negative": 0.4221204714206689,
         "Neutral": 0.40983396457957666,
         "Positive": 0.16804556399975434
      }
   },
   {
      "2017": {
         "Negative": 0.44605752613752825,
         "Neutral": 0.34420479853986735,
         "Positive": 0.2097376753226044
      }
   },
   {
      "2018": {
         "Negative": 0.5342185231323708,
         "Neutral": 0.2984335320573592,
         "Positive": 0.16734794481026996
      }
   },
   {
      "2019": {
         "Negative": 0.6259593262741976,
         "Neutral": 0.20858496610363378,
         "Positive": 0.16545570762216869
      }
   },
   {
      "2020": {
         "Negative": 0.6538853982808213,
         "Neutral": 0.19248891622339515,
         "Positive": 0.15362568549578356
      }
   },
   {
      "2021": {
         "Negative": 0.5894586635949707,
         "Neutral": 0.23694001618589428,
         "Positive": 0.173601320219135
      }
   },
   {
      "2022": {
         "Negative": 0.5987495729421034,
         "Neutral": 0.16808053882979618,
         "Positive": 0.23316988822810045
      }
   },
   {
      "2023": {
         "Negative": 0.41776802255617707,
         "Neutral": 0.23253007419945212,
         "Positive": 0.34970190324437084
      }
   }
]